README.md
setup.py
mondrian_rest/__init__.py
mondrian_rest/aggregation.py
mondrian_rest/client.py
mondrian_rest/identifier.py
mondrian_rest/test.py
mondrian_rest.egg-info/PKG-INFO
mondrian_rest.egg-info/SOURCES.txt
mondrian_rest.egg-info/dependency_links.txt
mondrian_rest.egg-info/not-zip-safe
mondrian_rest.egg-info/requires.txt
mondrian_rest.egg-info/top_level.txt