Metadata-Version: 1.0
Name: mondrian-rest
Version: 0.2
Summary: Python client for mondrian-rest
Home-page: http://github.com/Datawheel/mondrian-rest
Author: Manuel Aristaran - Datawheel
Author-email: manuel@jazzido.com
License: MIT
Platform: UNKNOWN
